xsimlab/__init__.py
xsimlab/_version.py
xsimlab/dot.py
xsimlab/drivers.py
xsimlab/formatting.py
xsimlab/hook.py
xsimlab/ipython.py
xsimlab/model.py
xsimlab/monitoring.py
xsimlab/process.py
xsimlab/stores.py
xsimlab/utils.py
xsimlab/validators.py
xsimlab/variable.py
xsimlab/xr_accessor.py
xsimlab/tests/__init__.py
xsimlab/tests/conftest.py
xsimlab/tests/fixture_model.py
xsimlab/tests/fixture_process.py
xsimlab/tests/test_dot.py
xsimlab/tests/test_drivers.py
xsimlab/tests/test_formatting.py
xsimlab/tests/test_hook.py
xsimlab/tests/test_ipython.py
xsimlab/tests/test_model.py
xsimlab/tests/test_monitoring.py
xsimlab/tests/test_process.py
xsimlab/tests/test_signals.py
xsimlab/tests/test_stores.py
xsimlab/tests/test_utils.py
xsimlab/tests/test_validators.py
xsimlab/tests/test_variable.py
xsimlab/tests/test_xr_accessor.py
xarray_simlab-0.5.0.dist-info/LICENSE
xarray_simlab-0.5.0.dist-info/METADATA
xarray_simlab-0.5.0.dist-info/WHEEL
xarray_simlab-0.5.0.dist-info/top_level.txt
xarray_simlab-0.5.0.dist-info/RECORD
