Metadata-Version: 2.1
Name: xarray-simlab
Version: 0.5.0
Summary: generic framework and xarray extension for computer model simulations
Home-page: http://github.com/benbovy/xarray-simlab
Maintainer: Benoit Bovy
Maintainer-email: benbovy@gmail.com
License: BSD-Clause3
Keywords: python xarray modelling simulation framework
Platform: UNKNOWN
Requires-Python: >=3.5
Requires-Dist: attrs (>=18.1.0)
Requires-Dist: dask
Requires-Dist: numpy
Requires-Dist: xarray (>=0.10.0)
Requires-Dist: zarr (>=2.3.0)
